paps/__init__.py
paps/changeInterface.py
paps/papsException.py
paps/person.py
paps/crowd/__init__.py
paps/crowd/controller.py
paps/crowd/pluginInterface.py
paps/si/__init__.py
paps/si/sensorClientAdapter.py
paps/si/sensorInterface.py
paps/si/sensorServerClientAdapter.py
paps/si/app/__init__.py
paps/si/app/message.py
paps/si/app/sensor.py
paps/si/app/sensorClient.py
paps/si/app/sensorServer.py
paps-0.2.4b0.dist-info/DESCRIPTION.rst
paps-0.2.4b0.dist-info/METADATA
paps-0.2.4b0.dist-info/RECORD
paps-0.2.4b0.dist-info/WHEEL
paps-0.2.4b0.dist-info/metadata.json
paps-0.2.4b0.dist-info/top_level.txt
