Metadata-Version: 2.0
Name: paps
Version: 0.2.4b0
Summary: Pi/Python-based Audience Participation System
Home-page: https://github.com/the01/python-paps
Author: d01 <Florian Jung>
Author-email: jungflor@gmail.com
License: MIT
Keywords: audience participation
Platform: UNKNOWN
Classifier: Development Status :: 2 - Pre-Alpha
Classifier: Intended Audience :: Developers
Classifier: License :: OSI Approved :: MIT License
Classifier: Natural Language :: English
Classifier: Programming Language :: Python :: 2
Classifier: Programming Language :: Python :: 2.7
Requires-Dist: enum34 (<1.2,>=1.1.2)
Requires-Dist: flotils (<0.4.0,>=0.3.0.a0)
Requires-Dist: future (>=0.15.2)
Requires-Dist: pytz (>=2015.7)
Requires-Dist: tzlocal (>=1.2,<1.3)
